vconpy/vcontacts_wrapper.py
vconpy/__init__.py
vconpy/bin/vcon
vcon_py-1.0.2.dist-info/RECORD
vcon_py-1.0.2.dist-info/WHEEL
vcon_py-1.0.2.dist-info/METADATA
