Metadata-Version: 2.2
Name: vcon-py
Version: 1.0.2
Summary: Python wheels and a wrapper for Vcontacts, a tool to compute surface areas in contact using the constrained Voronoi procedure.
Author: Thomas DesCôteaux
Author-Email: Rafael Najmanovich <rafael.najmanovich@umontreal.ca>
Classifier: Intended Audience :: Science/Research
Classifier: License :: OSI Approved :: GNU General Public License v3 or later (GPLv3+)
Classifier: Natural Language :: English
Project-URL: Homepage, https://github.com/NRGlab
Project-URL: Documentation, https://github.com/NRGlab/vcon-py/blob/main/README.md
Project-URL: Repository, https://github.com/NRGlab/vcon-py
Project-URL: Issues, https://github.com/NRGlab/vcon-py/issues
Requires-Python: >=3.9
